Metadata-Version: 2.1
Name: hashver
Version: 0.0.2
Summary: hashver is a python module to derive a unique numeric value from a version string and vice versa
Home-page: https://github.com/ashutoshkumr/python-hashver
Author: Ashutosh Kumar
Author-email: ashutoshk.akumar@gmail.com
License: UNKNOWN
Platform: UNKNOWN
Classifier: Programming Language :: Python :: 3
Classifier: Programming Language :: Python :: 2.7
Classifier: License :: OSI Approved :: MIT License
Classifier: Operating System :: OS Independent
